adopt/__init__.py
adopt/adopt.py
torch_adopt-0.1.0.dist-info/METADATA
torch_adopt-0.1.0.dist-info/WHEEL
torch_adopt-0.1.0.dist-info/licenses/LICENSE
torch_adopt-0.1.0.dist-info/RECORD
