Metadata-Version: 2.3
Name: torch-adopt
Version: 0.1.0
Summary: ADOPT: Modified Adam Can Converge with Any β2 with the Optimal Rate
Project-URL: Homepage, https://github.com/iShohei220/adopt
Project-URL: Bug Tracker, https://github.com/iShohei220/adopt/issues
Project-URL: Documentation, https://github.com/iShohei220/adopt
Project-URL: Research Paper, https://arxiv.org/abs/2411.02853
Author-email: Shohei Taniguchi <ishohei220@gmail.com>
Classifier: Intended Audience :: Science/Research
Classifier: License :: OSI Approved :: Apache Software License
Classifier: Operating System :: OS Independent
Classifier: Programming Language :: Python :: 3
Classifier: Programming Language :: Python :: 3.8
Classifier: Programming Language :: Python :: 3.9
Classifier: Programming Language :: Python :: 3.10
Classifier: Programming Language :: Python :: 3.11
Classifier: Topic :: Scientific/Engineering :: Artificial Intelligence
Requires-Python: >=3.8
Requires-Dist: torch>=2.5.0
